LICENSE
copier.yml
template/{{ project_name }}/.copier-answers.yml.jinja
template/{{ project_name }}/.gitignore
template/{{ project_name }}/.pre-commit-config.yaml.jinja
template/{{ project_name }}/.readthedocs.yml
template/{{ project_name }}/LICENSES-bundled.txt.jinja
template/{{ project_name }}/README.md.jinja
template/{{ project_name }}/noxfile.py.jinja
template/{{ project_name }}/pyproject.toml.jinja
template/{{ project_name }}/{% if backend == 'setuptools' and vcs == false %}MANIFEST.in{% endif %}.jinja
template/{{ project_name }}/{% if ci == 'gitlab' %}.gitlab-ci.yml{% endif %}.jinja
template/{{ project_name }}/{% if license=='Apache' %}LICENSE{% endif %}.jinja
template/{{ project_name }}/{% if license=='BSD' %}LICENSE{% endif %}.jinja
template/{{ project_name }}/{% if license=='MIT' %}LICENSE{% endif %}.jinja
template/{{ project_name }}/{% if vcs == true %}.git_archival.txt{% endif %}.jinja
template/{{ project_name }}/{% if vcs == true %}.gitattributes.txt{% endif %}.jinja
template/{{ project_name }}/docs/conf.py.jinja
template/{{ project_name }}/docs/index.md.jinja
template/{{ project_name }}/docs/refs.bib
template/{{ project_name }}/docs/_static/.gitkeep
template/{{ project_name }}/src/{{project_slug}}/__init__.py.jinja
template/{{ project_name }}/src/{{project_slug}}/entry_point.py.jinja
template/{{ project_name }}/src/{{project_slug}}/{% if mypy %}py.typed{% endif %}
template/{{ project_name }}/src/{{project_slug}}/{% if vcs %}_version.py{% endif %}
template/{{ project_name }}/src/{{project_slug}}/models/input/BasicReservoir.py
template/{{ project_name }}/src/{{project_slug}}/models/input/SPM.py
template/{{ project_name }}/src/{{project_slug}}/parameters/input/Chen2020.py
template/{{ project_name }}/tests/generated_project_tests/test_entry_points.py.jinja
template/{{ project_name }}/tests/user_tests/test_package.py.jinja
template/{{ project_name }}/{% if ci == 'github' %}.github{% endif %}/dependabot.yml
pybamm_cookie-0.1.2.dist-info/METADATA
pybamm_cookie-0.1.2.dist-info/WHEEL
pybamm_cookie-0.1.2.dist-info/entry_points.txt
pybamm_cookie-0.1.2.dist-info/licenses/LICENSE
pybamm_cookie-0.1.2.dist-info/RECORD
