Metadata-Version: 2.3
Name: pybamm-cookie
Version: 0.1.2
Summary: A template for creating battery modeling projects based on PyBaMM
Project-URL: Homepage, https://github.com/pybamm-team/pybamm-cookie
Project-URL: Bug Tracker, https://github.com/pybamm-team/pybamm-cookie/issues
Project-URL: Discussions, https://github.com/pybamm-team/pybamm-cookie/discussions
Project-URL: Changelog, https://github.com/pybamm-team/pybamm-cookie/releases
Author-email: Agriya Khetarpal <agriyakhetarpal@outlook.com>, Santhosh Sundaram <santhoshsundaram9650@gmail.com>
Maintainer-email: PyBaMM Team <pybamm@pybamm.org>
License-File: LICENSE
Classifier: Development Status :: 1 - Planning
Classifier: Intended Audience :: Developers
Classifier: Intended Audience :: Science/Research
Classifier: License :: OSI Approved :: BSD License
Classifier: Operating System :: OS Independent
Classifier: Programming Language :: Python
Classifier: Programming Language :: Python :: 3
Classifier: Programming Language :: Python :: 3 :: Only
Classifier: Programming Language :: Python :: 3.8
Classifier: Programming Language :: Python :: 3.9
Classifier: Programming Language :: Python :: 3.10
Classifier: Programming Language :: Python :: 3.11
Classifier: Topic :: Scientific/Engineering
Classifier: Typing :: Typed
Requires-Python: >=3.8
Requires-Dist: colorama
Requires-Dist: copier
Requires-Dist: jinja2-time
Provides-Extra: dev
Requires-Dist: nox[uv]; extra == 'dev'
Requires-Dist: pre-commit; extra == 'dev'
Requires-Dist: pytest-copie; extra == 'dev'
Requires-Dist: pytest-cov>=3; extra == 'dev'
Requires-Dist: pytest>=6; extra == 'dev'
Provides-Extra: docs
Requires-Dist: ipython; extra == 'docs'
Requires-Dist: myst-parser; extra == 'docs'
Requires-Dist: nbsphinx; extra == 'docs'
Requires-Dist: pydata-sphinx-theme; extra == 'docs'
Requires-Dist: sphinx; extra == 'docs'
Requires-Dist: sphinx-autobuild; extra == 'docs'
Requires-Dist: sphinx-copybutton; extra == 'docs'
Requires-Dist: sphinx-design; extra == 'docs'
Requires-Dist: sphinx-gallery; extra == 'docs'
Requires-Dist: sphinx-inline-tabs; extra == 'docs'
Requires-Dist: sphinx-last-updated-by-git; extra == 'docs'
Requires-Dist: sphinxcontrib-bibtex; extra == 'docs'
